zacks/__init__.py
zacks/__main__.py
zacks/downloader.py
zacks-1.1.3.dist-info/METADATA
zacks-1.1.3.dist-info/WHEEL
zacks-1.1.3.dist-info/entry_points.txt
zacks-1.1.3.dist-info/top_level.txt
zacks-1.1.3.dist-info/RECORD
