Metadata-Version: 2.1
Name: zacks
Version: 1.1.3
Requires-Dist: requests
